odoo9_addon_account_move_so_import-9.0.1.0.0.99.dev10-py2.7-nspkg.pth
odoo9_addon_account_move_so_import-9.0.1.0.0.99.dev10.dist-info/METADATA
odoo9_addon_account_move_so_import-9.0.1.0.0.99.dev10.dist-info/RECORD
odoo9_addon_account_move_so_import-9.0.1.0.0.99.dev10.dist-info/WHEEL
odoo9_addon_account_move_so_import-9.0.1.0.0.99.dev10.dist-info/namespace_packages.txt
odoo9_addon_account_move_so_import-9.0.1.0.0.99.dev10.dist-info/top_level.txt
odoo_addons/account_move_so_import/README.rst
odoo_addons/account_move_so_import/__init__.py
odoo_addons/account_move_so_import/__openerp__.py
odoo_addons/account_move_so_import/data/completion_rule_data.xml
odoo_addons/account_move_so_import/i18n/account_move_so_import.pot
odoo_addons/account_move_so_import/i18n/de.po
odoo_addons/account_move_so_import/i18n/es.po
odoo_addons/account_move_so_import/models/__init__.py
odoo_addons/account_move_so_import/models/account_move.py
odoo_addons/account_move_so_import/static/description/icon.png
odoo_addons/account_move_so_import/test/completion_so_test.yml
